pyprimosortega/primos.py
pyprimosortega-0.1.dist-info/LICENSE.txt
pyprimosortega-0.1.dist-info/METADATA
pyprimosortega-0.1.dist-info/WHEEL
pyprimosortega-0.1.dist-info/top_level.txt
pyprimosortega-0.1.dist-info/RECORD
